<?xml version="1.0" encoding="UTF-8"?>
<objects serializationModel="Studio.02.02.00">
	<object class="Event" id="{9140464d-5ce9-46b4-8ffb-5a4562e430a9}">
		<property name="name">
			<value>Nested Event 23</value>
		</property>
		<property name="outputFormat">
			<value>0</value>
		</property>
		<relationship name="folder">
			<destination>{89464453-2daf-4476-86c5-6b3b17e79b88}</destination>
		</relationship>
		<relationship name="mixer">
			<destination>{b40727c2-6c13-47cc-849e-f60261d17e4a}</destination>
		</relationship>
		<relationship name="masterTrack">
			<destination>{9a6bc679-bcc7-408a-bf16-e7cde392a128}</destination>
		</relationship>
		<relationship name="mixerInput">
			<destination>{453dc84c-ce36-4013-bd67-77b11c563dce}</destination>
		</relationship>
		<relationship name="automatableProperties">
			<destination>{a17416fe-ab6c-425c-b201-1b868a1e6e69}</destination>
		</relationship>
		<relationship name="markerTracks">
			<destination>{9b508558-0292-4560-b6b4-2684f90ad161}</destination>
		</relationship>
		<relationship name="groupTracks">
			<destination>{8467b38d-0271-406b-894c-0e0305ef91ce}</destination>
		</relationship>
		<relationship name="timeline">
			<destination>{0702c6a3-26fd-4a33-8ddc-b078093f8c75}</destination>
		</relationship>
	</object>
	<object class="EventMixer" id="{b40727c2-6c13-47cc-849e-f60261d17e4a}">
		<relationship name="masterBus">
			<destination>{8688212a-096a-4036-bc5b-b2b685253f23}</destination>
		</relationship>
	</object>
	<object class="MasterTrack" id="{9a6bc679-bcc7-408a-bf16-e7cde392a128}">
		<property name="uiTrackHeight">
			<value>28</value>
		</property>
		<relationship name="mixerGroup">
			<destination>{8688212a-096a-4036-bc5b-b2b685253f23}</destination>
		</relationship>
	</object>
	<object class="MixerInput" id="{453dc84c-ce36-4013-bd67-77b11c563dce}">
		<relationship name="effectChain">
			<destination>{fe684b8f-80be-49c0-9317-1c82a4667c96}</destination>
		</relationship>
		<relationship name="panner">
			<destination>{1bd36233-0d73-40d6-b395-e0da52dfba43}</destination>
		</relationship>
	</object>
	<object class="EventAutomatableProperties" id="{a17416fe-ab6c-425c-b201-1b868a1e6e69}" />
	<object class="MarkerTrack" id="{9b508558-0292-4560-b6b4-2684f90ad161}">
		<property name="uiTrackHeight">
			<value>100</value>
		</property>
	</object>
	<object class="GroupTrack" id="{8467b38d-0271-406b-894c-0e0305ef91ce}">
		<property name="uiTrackHeight">
			<value>100</value>
		</property>
		<relationship name="modules">
			<destination>{1d966293-8f2c-4c00-b352-1b01dfb3d116}</destination>
		</relationship>
		<relationship name="mixerGroup">
			<destination>{5f68eb0d-de88-4184-9693-efac7ac4ff0f}</destination>
		</relationship>
	</object>
	<object class="Timeline" id="{0702c6a3-26fd-4a33-8ddc-b078093f8c75}">
		<relationship name="modules">
			<destination>{1d966293-8f2c-4c00-b352-1b01dfb3d116}</destination>
		</relationship>
	</object>
	<object class="EventMixerMaster" id="{8688212a-096a-4036-bc5b-b2b685253f23}">
		<relationship name="effectChain">
			<destination>{76e6a184-21d4-4e8e-a0e8-f49380591e27}</destination>
		</relationship>
		<relationship name="panner">
			<destination>{96978e9b-d9eb-41bd-b935-6e33908de303}</destination>
		</relationship>
		<relationship name="mixer">
			<destination>{b40727c2-6c13-47cc-849e-f60261d17e4a}</destination>
		</relationship>
	</object>
	<object class="MixerBusEffectChain" id="{fe684b8f-80be-49c0-9317-1c82a4667c96}">
		<relationship name="effects">
			<destination>{b840fa5c-3d50-44be-988f-5d2cd14e5033}</destination>
		</relationship>
	</object>
	<object class="MixerBusPanner" id="{1bd36233-0d73-40d6-b395-e0da52dfba43}" />
	<object class="MultiSound" id="{1d966293-8f2c-4c00-b352-1b01dfb3d116}">
		<property name="isAsync">
			<value>true</value>
		</property>
		<property name="length">
			<value>2</value>
		</property>
		<property name="looping">
			<value>true</value>
		</property>
		<property name="playCount">
			<value>2</value>
		</property>
		<property name="playlistMode">
			<value>2</value>
		</property>
		<relationship name="sounds">
			<destination>{5e93304c-97d5-480a-9646-e2011020d18c}</destination>
			<destination>{fff5dc3f-0df2-4c06-9265-bc62f78fef4d}</destination>
		</relationship>
	</object>
	<object class="EventMixerGroup" id="{5f68eb0d-de88-4184-9693-efac7ac4ff0f}">
		<property name="name">
			<value>Audio 1</value>
		</property>
		<relationship name="effectChain">
			<destination>{837813c6-6b59-4508-b51a-4ed2dfab5322}</destination>
		</relationship>
		<relationship name="panner">
			<destination>{eb91a296-0560-4be8-9007-826eb0131f37}</destination>
		</relationship>
		<relationship name="output">
			<destination>{8688212a-096a-4036-bc5b-b2b685253f23}</destination>
		</relationship>
	</object>
	<object class="MixerBusEffectChain" id="{76e6a184-21d4-4e8e-a0e8-f49380591e27}">
		<relationship name="effects">
			<destination>{1c054347-5dc0-4e2b-9074-b7ee801a4c8c}</destination>
		</relationship>
	</object>
	<object class="MixerBusPanner" id="{96978e9b-d9eb-41bd-b935-6e33908de303}" />
	<object class="MixerBusFader" id="{b840fa5c-3d50-44be-988f-5d2cd14e5033}" />
	<object class="EventSound" id="{5e93304c-97d5-480a-9646-e2011020d18c}">
		<relationship name="parameters">
			<destination>{07497259-4ca3-4931-8990-4c583719f424}</destination>
		</relationship>
		<relationship name="event">
			<destination>{da4c27d4-8e7f-414a-a7e6-07b7f6dc2077}</destination>
		</relationship>
	</object>
	<object class="EventSound" id="{fff5dc3f-0df2-4c06-9265-bc62f78fef4d}">
		<relationship name="parameters">
			<destination>{42bbcf38-fb4a-4af5-9af5-68432c0e4628}</destination>
		</relationship>
		<relationship name="event">
			<destination>{dae45861-1fbb-4e61-8d69-7adb562e3fe4}</destination>
		</relationship>
	</object>
	<object class="MixerBusEffectChain" id="{837813c6-6b59-4508-b51a-4ed2dfab5322}">
		<relationship name="effects">
			<destination>{e7e7270d-05f1-4179-8724-6a48baf891c3}</destination>
		</relationship>
	</object>
	<object class="MixerBusPanner" id="{eb91a296-0560-4be8-9007-826eb0131f37}" />
	<object class="MixerBusFader" id="{1c054347-5dc0-4e2b-9074-b7ee801a4c8c}" />
	<object class="ParameterProperty" id="{07497259-4ca3-4931-8990-4c583719f424}">
		<relationship name="parameter">
			<destination>{ed9fa66d-04eb-4e82-bb55-87b4343dd11c}</destination>
		</relationship>
	</object>
	<object class="ParameterProperty" id="{42bbcf38-fb4a-4af5-9af5-68432c0e4628}">
		<relationship name="parameter">
			<destination>{4232e834-9515-4dde-af77-7e208d25bca5}</destination>
		</relationship>
	</object>
	<object class="MixerBusFader" id="{e7e7270d-05f1-4179-8724-6a48baf891c3}" />
</objects>