<?xml version="1.0" encoding="UTF-8"?>
<objects serializationModel="Studio.02.02.00">
	<object class="Event" id="{a1213daf-286b-42f2-9290-d30977a0edff}">
		<property name="name">
			<value>Digging Ground Finish</value>
		</property>
		<property name="outputFormat">
			<value>1</value>
		</property>
		<relationship name="folder">
			<destination>{7290564b-1313-4db8-a77a-f78295fa671d}</destination>
		</relationship>
		<relationship name="mixer">
			<destination>{1a8a1869-5155-482a-9b2d-4e8f886a527c}</destination>
		</relationship>
		<relationship name="masterTrack">
			<destination>{8c04c5f0-586b-41c5-9958-0fee862c7ab5}</destination>
		</relationship>
		<relationship name="mixerInput">
			<destination>{bd0d3159-5398-448c-a54b-c261b16af9ce}</destination>
		</relationship>
		<relationship name="automatableProperties">
			<destination>{ac94b41b-2825-4f5d-b074-bcaec5a31d10}</destination>
		</relationship>
		<relationship name="markerTracks">
			<destination>{ea93ced8-a1bf-48d6-8d2c-bb8ea13e801a}</destination>
		</relationship>
		<relationship name="groupTracks">
			<destination>{99e45a46-92e3-4a4c-8fd2-b0aa478a1def}</destination>
		</relationship>
		<relationship name="timeline">
			<destination>{926a87ce-4732-410f-9af6-cbbef6c91efa}</destination>
		</relationship>
		<relationship name="banks">
			<destination>{3f7eb6c9-7e80-443c-af86-f7734eda7b1c}</destination>
		</relationship>
	</object>
	<object class="EventMixer" id="{1a8a1869-5155-482a-9b2d-4e8f886a527c}">
		<relationship name="masterBus">
			<destination>{0ffbe807-3cba-49dd-88a3-d36418b2d85a}</destination>
		</relationship>
	</object>
	<object class="MasterTrack" id="{8c04c5f0-586b-41c5-9958-0fee862c7ab5}">
		<property name="uiTrackHeight">
			<value>28</value>
		</property>
		<relationship name="mixerGroup">
			<destination>{0ffbe807-3cba-49dd-88a3-d36418b2d85a}</destination>
		</relationship>
	</object>
	<object class="MixerInput" id="{bd0d3159-5398-448c-a54b-c261b16af9ce}">
		<relationship name="effectChain">
			<destination>{02dcfc9b-eecb-4f3f-8914-9d9586bb4ff4}</destination>
		</relationship>
		<relationship name="panner">
			<destination>{328d1386-c540-4fb5-912c-ddfc071518d8}</destination>
		</relationship>
		<relationship name="output">
			<destination>{f1b38f9b-0b52-402e-8f48-52d146981120}</destination>
		</relationship>
	</object>
	<object class="EventAutomatableProperties" id="{ac94b41b-2825-4f5d-b074-bcaec5a31d10}" />
	<object class="MarkerTrack" id="{ea93ced8-a1bf-48d6-8d2c-bb8ea13e801a}">
		<property name="uiTrackHeight">
			<value>100</value>
		</property>
	</object>
	<object class="GroupTrack" id="{99e45a46-92e3-4a4c-8fd2-b0aa478a1def}">
		<property name="uiTrackHeight">
			<value>100</value>
		</property>
		<relationship name="modules">
			<destination>{21f5eeef-5957-406e-be2d-3f266e554c8e}</destination>
		</relationship>
		<relationship name="mixerGroup">
			<destination>{63d2e299-2e0e-4fb0-8332-5e85d9ec4c10}</destination>
		</relationship>
	</object>
	<object class="Timeline" id="{926a87ce-4732-410f-9af6-cbbef6c91efa}">
		<relationship name="modules">
			<destination>{21f5eeef-5957-406e-be2d-3f266e554c8e}</destination>
		</relationship>
	</object>
	<object class="EventMixerMaster" id="{0ffbe807-3cba-49dd-88a3-d36418b2d85a}">
		<relationship name="effectChain">
			<destination>{ea8cb3e6-7569-4604-a7bd-892ebc0a3b56}</destination>
		</relationship>
		<relationship name="panner">
			<destination>{69163784-9d5b-4955-93e0-e2d991d13a25}</destination>
		</relationship>
		<relationship name="mixer">
			<destination>{1a8a1869-5155-482a-9b2d-4e8f886a527c}</destination>
		</relationship>
	</object>
	<object class="MixerBusEffectChain" id="{02dcfc9b-eecb-4f3f-8914-9d9586bb4ff4}">
		<relationship name="effects">
			<destination>{095a2db3-ee7d-4e0d-8af0-ed35d55b7c95}</destination>
		</relationship>
	</object>
	<object class="MixerBusPanner" id="{328d1386-c540-4fb5-912c-ddfc071518d8}" />
	<object class="SingleSound" id="{21f5eeef-5957-406e-be2d-3f266e554c8e}">
		<property name="length">
			<value>2.3599999999999999</value>
		</property>
		<property name="timelockedOffset">
			<value>0.12000000000000001</value>
		</property>
		<relationship name="audioFile">
			<destination>{ebf4ff4b-fa5c-49ac-9fc3-1cb4ebfb14f1}</destination>
		</relationship>
	</object>
	<object class="EventMixerGroup" id="{63d2e299-2e0e-4fb0-8332-5e85d9ec4c10}">
		<property name="volume">
			<value>5</value>
		</property>
		<property name="name">
			<value>Audio 1</value>
		</property>
		<relationship name="effectChain">
			<destination>{84949d32-e645-408e-925d-4daf4ec8a827}</destination>
		</relationship>
		<relationship name="panner">
			<destination>{be2680ab-84ad-4bf9-999d-0afff0ac7441}</destination>
		</relationship>
		<relationship name="output">
			<destination>{0ffbe807-3cba-49dd-88a3-d36418b2d85a}</destination>
		</relationship>
	</object>
	<object class="MixerBusEffectChain" id="{ea8cb3e6-7569-4604-a7bd-892ebc0a3b56}">
		<relationship name="effects">
			<destination>{259f1556-1204-472c-82d1-c8c42f0929a8}</destination>
		</relationship>
	</object>
	<object class="MixerBusPanner" id="{69163784-9d5b-4955-93e0-e2d991d13a25}" />
	<object class="MixerBusFader" id="{095a2db3-ee7d-4e0d-8af0-ed35d55b7c95}" />
	<object class="MixerBusEffectChain" id="{84949d32-e645-408e-925d-4daf4ec8a827}">
		<relationship name="effects">
			<destination>{0264fb06-0d7e-4f28-94a6-738d46f00324}</destination>
		</relationship>
	</object>
	<object class="MixerBusPanner" id="{be2680ab-84ad-4bf9-999d-0afff0ac7441}" />
	<object class="MixerBusFader" id="{259f1556-1204-472c-82d1-c8c42f0929a8}" />
	<object class="MixerBusFader" id="{0264fb06-0d7e-4f28-94a6-738d46f00324}" />
</objects>