<?xml version="1.0" encoding="UTF-8"?>
<objects serializationModel="Studio.02.02.00">
	<object class="Event" id="{dc67d968-7ec1-41e6-9d0e-bd4e01299f7f}">
		<property name="name">
			<value>Nested Event 8</value>
		</property>
		<property name="outputFormat">
			<value>1</value>
		</property>
		<relationship name="folder">
			<destination>{5cddb7e1-c5b6-4a7f-85ff-cea2c80b45ec}</destination>
		</relationship>
		<relationship name="mixer">
			<destination>{7d2ebe3a-d4d9-49f1-b197-e44f27a8ee37}</destination>
		</relationship>
		<relationship name="masterTrack">
			<destination>{02623044-fc48-4241-b04d-96e72a63e410}</destination>
		</relationship>
		<relationship name="mixerInput">
			<destination>{66aaa8ff-fba4-4504-b39a-004f6b200069}</destination>
		</relationship>
		<relationship name="automatableProperties">
			<destination>{e273ac3d-b466-48b1-8da1-95bdc9b4d173}</destination>
		</relationship>
		<relationship name="markerTracks">
			<destination>{fe247d12-387d-40f4-bc6e-a84981533c26}</destination>
		</relationship>
		<relationship name="groupTracks">
			<destination>{7f3e419d-0c54-47b2-9563-f10ba142bcf5}</destination>
		</relationship>
		<relationship name="timeline">
			<destination>{4a3d9659-8642-4d3d-b70b-9e6e23fcc511}</destination>
		</relationship>
	</object>
	<object class="EventMixer" id="{7d2ebe3a-d4d9-49f1-b197-e44f27a8ee37}">
		<relationship name="masterBus">
			<destination>{e7501960-8412-4b79-b867-01b72c2717e3}</destination>
		</relationship>
	</object>
	<object class="MasterTrack" id="{02623044-fc48-4241-b04d-96e72a63e410}">
		<property name="uiTrackHeight">
			<value>28</value>
		</property>
		<relationship name="mixerGroup">
			<destination>{e7501960-8412-4b79-b867-01b72c2717e3}</destination>
		</relationship>
	</object>
	<object class="MixerInput" id="{66aaa8ff-fba4-4504-b39a-004f6b200069}">
		<relationship name="effectChain">
			<destination>{8f1370d0-5cb7-4dd7-8bf6-0b48ed22fa2e}</destination>
		</relationship>
		<relationship name="panner">
			<destination>{095285f7-cfa6-410c-b058-7da3769b15e2}</destination>
		</relationship>
	</object>
	<object class="EventAutomatableProperties" id="{e273ac3d-b466-48b1-8da1-95bdc9b4d173}" />
	<object class="MarkerTrack" id="{fe247d12-387d-40f4-bc6e-a84981533c26}">
		<property name="uiTrackHeight">
			<value>100</value>
		</property>
	</object>
	<object class="GroupTrack" id="{7f3e419d-0c54-47b2-9563-f10ba142bcf5}">
		<property name="uiTrackHeight">
			<value>100</value>
		</property>
		<relationship name="modules">
			<destination>{64462887-e4ce-4f1c-a953-fc780c7c123c}</destination>
		</relationship>
		<relationship name="mixerGroup">
			<destination>{6d6aeb40-af50-44ff-9487-32b688a09c4a}</destination>
		</relationship>
	</object>
	<object class="Timeline" id="{4a3d9659-8642-4d3d-b70b-9e6e23fcc511}">
		<relationship name="modules">
			<destination>{64462887-e4ce-4f1c-a953-fc780c7c123c}</destination>
		</relationship>
	</object>
	<object class="EventMixerMaster" id="{e7501960-8412-4b79-b867-01b72c2717e3}">
		<relationship name="effectChain">
			<destination>{d9e72d0e-646b-4cb3-b158-8a616540e00a}</destination>
		</relationship>
		<relationship name="panner">
			<destination>{fb3efdff-c957-4478-956a-5c6eff7aff57}</destination>
		</relationship>
		<relationship name="mixer">
			<destination>{7d2ebe3a-d4d9-49f1-b197-e44f27a8ee37}</destination>
		</relationship>
	</object>
	<object class="MixerBusEffectChain" id="{8f1370d0-5cb7-4dd7-8bf6-0b48ed22fa2e}">
		<relationship name="effects">
			<destination>{d3d9caef-77aa-4cd5-ad0c-07f1f1b49673}</destination>
		</relationship>
	</object>
	<object class="MixerBusPanner" id="{095285f7-cfa6-410c-b058-7da3769b15e2}" />
	<object class="MultiSound" id="{64462887-e4ce-4f1c-a953-fc780c7c123c}">
		<property name="isAsync">
			<value>true</value>
		</property>
		<property name="length">
			<value>2</value>
		</property>
		<property name="looping">
			<value>true</value>
		</property>
		<property name="playCount">
			<value>3</value>
		</property>
		<property name="playlistMode">
			<value>2</value>
		</property>
		<relationship name="sounds">
			<destination>{8bf3942e-793f-49c0-978d-5813be661e3b}</destination>
			<destination>{65c71742-4a58-4624-8f19-1700accb1cd7}</destination>
			<destination>{1632c2f0-fe5a-437f-b8ba-2020d2a66068}</destination>
		</relationship>
	</object>
	<object class="EventMixerGroup" id="{6d6aeb40-af50-44ff-9487-32b688a09c4a}">
		<property name="name">
			<value>Audio 1</value>
		</property>
		<relationship name="effectChain">
			<destination>{bbe1c045-b8d4-4e76-994a-a03023851955}</destination>
		</relationship>
		<relationship name="panner">
			<destination>{0fe6dc64-883a-4adc-bc31-a94d6de191d8}</destination>
		</relationship>
		<relationship name="output">
			<destination>{e7501960-8412-4b79-b867-01b72c2717e3}</destination>
		</relationship>
	</object>
	<object class="MixerBusEffectChain" id="{d9e72d0e-646b-4cb3-b158-8a616540e00a}">
		<relationship name="effects">
			<destination>{deed7884-1e5b-4a12-ab47-340e27899222}</destination>
		</relationship>
	</object>
	<object class="MixerBusPanner" id="{fb3efdff-c957-4478-956a-5c6eff7aff57}" />
	<object class="MixerBusFader" id="{d3d9caef-77aa-4cd5-ad0c-07f1f1b49673}" />
	<object class="SingleSound" id="{8bf3942e-793f-49c0-978d-5813be661e3b}">
		<relationship name="audioFile">
			<destination>{46a75530-5bc0-4c84-adfc-ee450acf3361}</destination>
		</relationship>
	</object>
	<object class="EventSound" id="{65c71742-4a58-4624-8f19-1700accb1cd7}">
		<property name="name">
			<value>250ms</value>
		</property>
		<relationship name="event">
			<destination>{7f207b31-767b-429c-94f0-a9defcc1ee4c}</destination>
		</relationship>
	</object>
	<object class="SingleSound" id="{1632c2f0-fe5a-437f-b8ba-2020d2a66068}">
		<relationship name="audioFile">
			<destination>{38a1c2d4-e192-4cc3-a6b6-bfc33a5a2732}</destination>
		</relationship>
	</object>
	<object class="MixerBusEffectChain" id="{bbe1c045-b8d4-4e76-994a-a03023851955}">
		<relationship name="effects">
			<destination>{771b3a3e-138e-4076-bb1f-a20dae0b3996}</destination>
		</relationship>
	</object>
	<object class="MixerBusPanner" id="{0fe6dc64-883a-4adc-bc31-a94d6de191d8}" />
	<object class="MixerBusFader" id="{deed7884-1e5b-4a12-ab47-340e27899222}" />
	<object class="MixerBusFader" id="{771b3a3e-138e-4076-bb1f-a20dae0b3996}" />
</objects>