<?xml version="1.0" encoding="UTF-8"?>
<objects serializationModel="Studio.02.00.00">
	<object class="AudioFile" id="{1c1fbf36-daff-4d7b-9bb5-5995d18fa6b8}">
		<property name="assetPath">
			<value>Voice Acting/Quests/Barbarian/Leader/1-18-2(2a)-PELIAS-AndrewPond-Edited-MouthDeClicked.mp3</value>
		</property>
		<property name="isStreaming">
			<value>true</value>
		</property>
		<property name="frequencyInKHz">
			<value>44.0999985</value>
		</property>
		<property name="channelCount">
			<value>1</value>
		</property>
		<property name="length">
			<value>1.9069387755102041</value>
		</property>
		<relationship name="masterAssetFolder">
			<destination>{7d27621b-288c-4414-a7b5-99d3cfd180cf}</destination>
		</relationship>
	</object>
</objects>
