<?xml version="1.0" encoding="UTF-8"?>
<objects serializationModel="Studio.02.00.00">
	<object class="AudioFile" id="{65062d56-f59a-4b23-a9e0-eba773cdd633}">
		<property name="assetPath">
			<value>Voice Acting/NPCs/Geologist/Female/7-1-DwarvenGeologistFemale-Incognerdo-Edited-DC.wav</value>
		</property>
		<property name="isStreaming">
			<value>true</value>
		</property>
		<property name="frequencyInKHz">
			<value>44.0999985</value>
		</property>
		<property name="channelCount">
			<value>1</value>
		</property>
		<property name="length">
			<value>4.3448526077097505</value>
		</property>
		<relationship name="masterAssetFolder">
			<destination>{7d27621b-288c-4414-a7b5-99d3cfd180cf}</destination>
		</relationship>
	</object>
</objects>
