<?xml version="1.0" encoding="UTF-8"?>
<objects serializationModel="Studio.02.00.00">
	<object class="AudioFile" id="{da64e589-0b47-4060-9254-89cfb96e5f27}">
		<property name="assetPath">
			<value>Voice Acting/Intro/Common/Intro-Common-Part3-v2.mp3</value>
		</property>
		<property name="isStreaming">
			<value>true</value>
		</property>
		<property name="frequencyInKHz">
			<value>44.0999985</value>
		</property>
		<property name="channelCount">
			<value>1</value>
		</property>
		<property name="length">
			<value>9.8481632653061233</value>
		</property>
		<relationship name="masterAssetFolder">
			<destination>{7d27621b-288c-4414-a7b5-99d3cfd180cf}</destination>
		</relationship>
	</object>
</objects>
