<?xml version="1.0" encoding="UTF-8"?>
<objects serializationModel="Studio.02.00.00">
	<object class="AudioFile" id="{e1286c09-3aa8-4415-a9d7-fec2bb507087}">
		<property name="assetPath">
			<value>Monsters/Dog/animal-dog-labrador-yelp-whine-internal.wav</value>
		</property>
		<property name="frequencyInKHz">
			<value>96</value>
		</property>
		<property name="channelCount">
			<value>2</value>
		</property>
		<property name="length">
			<value>1.45996875</value>
		</property>
		<relationship name="masterAssetFolder">
			<destination>{7d27621b-288c-4414-a7b5-99d3cfd180cf}</destination>
		</relationship>
	</object>
</objects>
